README.txt
setup.py
skimpyGimpy/KiPNG.py
skimpyGimpy/__init__.py
skimpyGimpy/bdf.py
skimpyGimpy/canvas.py
skimpyGimpy/cursive.py
skimpyGimpy/getparm.py
skimpyGimpy/httpTempFile.py
skimpyGimpy/pngBarChart.py
skimpyGimpy/pngPieChart.py
skimpyGimpy/skimpyAPI.py
skimpyGimpy/skimpyGimpy.py
skimpyGimpy/waveTools.py
skimpyGimpy.egg-info/PKG-INFO
skimpyGimpy.egg-info/SOURCES.txt
skimpyGimpy.egg-info/dependency_links.txt
skimpyGimpy.egg-info/top_level.txt