Metadata-Version: 1.0
Name: skimpyGimpy
Version: 1.4
Summary: Skimpy Gimpy Audio/visual Tools
Home-page: http://skimpygimpy.sourceforge.net/
Author: Aaron Watters
Author-email: aaronwmail-sourceforge@yahoo.com
License: UNKNOWN
Download-URL: http://skimpygimpy.googlecode.com/files/skimpyGimpy-1.3-py2.4.egg
Platform: Python 2.4 +
Classifier: Topic :: Multimedia :: Sound/Audio
Classifier: Topic :: Multimedia :: Sound/Audio :: Sound Synthesis
Classifier: Topic :: Multimedia :: Sound/Audio :: Speech
